{
  "success": true,
  "query": "Rustic log cabin porch forest wilderness New England",
  "count": 3,
  "ranked": false,
  "results": [
    {
      "original_url": "https://sfile.chatglm.cn/images-ppt/89ff79ca7ee8.jpg",
      "caption": "",
      "source": "Vermont Explored",
      "original_width": "1200px",
      "original_height": "700px"
    },
    {
      "original_url": "https://sfile.chatglm.cn/images-ppt/8e56f9d35043.jpeg",
      "caption": "",
      "source": "Airbnb",
      "original_width": "1200px",
      "original_height": "900px"
    },
    {
      "original_url": "https://sfile.chatglm.cn/images-ppt/01fbbeb2c9df.jpg",
      "caption": "",
      "source": "LandSearch",
      "original_width": "1680px",
      "original_height": "1260px"
    }
  ]
}