{
  "success": true,
  "query": "deep pine forest sunlight trail New England wilderness",
  "count": 3,
  "ranked": false,
  "results": [
    {
      "original_url": "https://sfile.chatglm.cn/images-ppt/a3ab65faa886.jpg",
      "caption": "",
      "source": "Alamy",
      "original_width": "823px",
      "original_height": "1390px"
    },
    {
      "original_url": "https://sfile.chatglm.cn/images-ppt/abb4774026d7.jpg",
      "caption": "",
      "source": "Hiking in Maine",
      "original_width": "768px",
      "original_height": "1024px"
    },
    {
      "original_url": "https://sfile.chatglm.cn/images-ppt/a1ec4f3b9722.jpg",
      "caption": "",
      "source": "Matador Network",
      "original_width": "1200px",
      "original_height": "853px"
    }
  ]
}